hakalab_framework/__init__.py
hakalab_framework/cli.py
hakalab_framework/cli_html_report.py
hakalab_framework/core/__init__.py
hakalab_framework/core/behave_html_integration.py
hakalab_framework/core/context_helpers.py
hakalab_framework/core/element_locator.py
hakalab_framework/core/environment_config.py
hakalab_framework/core/html_reporter.py
hakalab_framework/core/report_generator.py
hakalab_framework/core/screenshot_manager.py
hakalab_framework/core/step_suggester.py
hakalab_framework/core/variable_manager.py
hakalab_framework/core/video_manager.py
hakalab_framework/examples/html_report_example.py
hakalab_framework/integrations/__init__.py
hakalab_framework/integrations/behave_hooks.py
hakalab_framework/integrations/jira_integration.py
hakalab_framework/integrations/xray_integration.py
hakalab_framework/steps/__init__.py
hakalab_framework/steps/advanced_input_steps.py
hakalab_framework/steps/advanced_steps.py
hakalab_framework/steps/assertion_steps.py
hakalab_framework/steps/combobox_steps.py
hakalab_framework/steps/csv_file_steps.py
hakalab_framework/steps/data_extraction_steps.py
hakalab_framework/steps/drag_drop_steps.py
hakalab_framework/steps/environment_steps.py
hakalab_framework/steps/file_steps.py
hakalab_framework/steps/iframe_steps.py
hakalab_framework/steps/interaction_steps.py
hakalab_framework/steps/jira_xray_steps.py
hakalab_framework/steps/keyboard_mouse_steps.py
hakalab_framework/steps/modal_steps.py
hakalab_framework/steps/navigation_steps.py
hakalab_framework/steps/salesforce_steps.py
hakalab_framework/steps/scroll_steps.py
hakalab_framework/steps/table_steps.py
hakalab_framework/steps/timing_steps.py
hakalab_framework/steps/variable_steps.py
hakalab_framework/steps/wait_steps.py
hakalab_framework/steps/window_steps.py
hakalab_framework/templates/__init__.py
hakalab_framework/templates/environment.py
hakalab_framework/templates/environment_with_html_report.py
hakalab_framework/templates/environment_with_jira_xray.py
hakalab_framework-1.2.23.dist-info/licenses/LICENSE
hakalab_framework-1.2.23.dist-info/METADATA
hakalab_framework-1.2.23.dist-info/WHEEL
hakalab_framework-1.2.23.dist-info/entry_points.txt
hakalab_framework-1.2.23.dist-info/top_level.txt
hakalab_framework-1.2.23.dist-info/RECORD
