Metadata-Version: 2.4
Name: hakalab-framework
Version: 1.2.23
Summary: Framework completo de pruebas funcionales con Playwright y Behave
Home-page: https://github.com/pipefariashaka/hakalab-framework.git
Author: Felipe Farias
Author-email: Felipe Farias <felipe.farias@hakalab.com>
Maintainer-email: Felipe Farias <felipe.farias@hakalab.com>
License: MIT
Project-URL: Homepage, https://github.com/pipefariashaka/hakalab-framework
Project-URL: Repository, https://github.com/pipefariashaka/hakalab-framework
Project-URL: Documentation, https://github.com/pipefariashaka/hakalab-framework#readme
Project-URL: Bug Tracker, https://github.com/pipefariashaka/hakalab-framework/issues
Keywords: playwright,behave,bdd,testing,automation,functional-testing
Classifier: Development Status :: 4 - Beta
Classifier: Intended Audience :: Developers
Classifier: Topic :: Software Development :: Testing
Classifier: License :: OSI Approved :: MIT License
Classifier: Programming Language :: Python :: 3
Classifier: Programming Language :: Python :: 3.8
Classifier: Programming Language :: Python :: 3.9
Classifier: Programming Language :: Python :: 3.10
Classifier: Programming Language :: Python :: 3.11
Classifier: Programming Language :: Python :: 3.12
Classifier: Operating System :: OS Independent
Requires-Python: >=3.8
License-File: LICENSE
Requires-Dist: playwright>=1.57.0
Requires-Dist: behave>=1.3.3
Requires-Dist: python-dotenv>=1.0.0
Requires-Dist: jsonschema>=4.20.0
Requires-Dist: click>=8.0.0
Requires-Dist: rich>=13.0.0
Requires-Dist: jinja2>=3.0.0
Requires-Dist: requests>=2.28.0
Provides-Extra: dev
Requires-Dist: pytest>=7.0.0; extra == "dev"
Requires-Dist: black>=22.0.0; extra == "dev"
Requires-Dist: flake8>=4.0.0; extra == "dev"
Requires-Dist: mypy>=0.950; extra == "dev"
Requires-Dist: pre-commit>=2.20.0; extra == "dev"
Provides-Extra: allure
Requires-Dist: allure-commandline>=2.20.0; extra == "allure"
Dynamic: author
Dynamic: home-page
Dynamic: license-file
Dynamic: requires-python
